{"projects":[{"id":7369585,"name":"LOOK TV","published_on":1389829313,"created_on":1362008102,"modified_on":1389829633,"url":"http:\/\/www.behance.net\/gallery\/LOOK-TV\/7369585","privacy":"public","fields":["Graphic Design","Motion Graphics"],"covers":{"404":"http:\/\/m1.behance.net\/rendition\/projects\/7369585\/404\/33bc8e81dae700028fc26b9eaac4bbe4.jpg","202":"http:\/\/m1.behance.net\/rendition\/projects\/7369585\/orig\/33bc8e81dae700028fc26b9eaac4bbe4.jpg","230":"http:\/\/m1.behance.net\/rendition\/projects\/7369585\/230\/33bc8e81dae700028fc26b9eaac4bbe4.jpg","115":"http:\/\/m1.behance.net\/rendition\/projects\/7369585\/115\/33bc8e81dae700028fc26b9eaac4bbe4.jpg"},"mature_content":0,"mature_access":"allowed","owners":[{"id":2285079,"first_name":"Gerard","last_name":"Mallandrich","username":"gmallandrich","city":"Barcelona","state":"","country":"Spain","company":"","occupation":"Graphic Designer","created_on":1362003381,"url":"http:\/\/www.behance.net\/gmallandrich","images":{"50":"http:\/\/a2.behance.net\/img\/profile\/no-image-50.jpg?cb=586349672","115":"http:\/\/a2.behance.net\/img\/profile\/no-image-115.jpg?cb=586349672","138":"http:\/\/a2.behance.net\/img\/profile\/no-image-138.jpg?cb=586349672"},"display_name":"Gerard Mallandrich","fields":["Graphic Design","Motion Graphics","Information Architecture"]}],"stats":{"views":25,"appreciations":1,"comments":0},"for_sale":0},{"id":4901883,"name":"Dilli Haat - Signage system","published_on":1389190679,"created_on":1345655164,"modified_on":1389286011,"url":"http:\/\/www.behance.net\/gallery\/Dilli-Haat-Signage-system\/4901883","privacy":"public","fields":["Exhibition Design","Graphic Design"],"covers":{"404":"http:\/\/m1.behance.net\/rendition\/projects\/4901883\/404\/1bcd76adaa3bdaf8863ecdb5843c165f.jpg","202":"http:\/\/m1.behance.net\/rendition\/projects\/4901883\/orig\/1bcd76adaa3bdaf8863ecdb5843c165f.jpg","230":"http:\/\/m1.behance.net\/rendition\/projects\/4901883\/230\/1bcd76adaa3bdaf8863ecdb5843c165f.jpg","115":"http:\/\/m1.behance.net\/rendition\/projects\/4901883\/115\/1bcd76adaa3bdaf8863ecdb5843c165f.jpg"},"mature_content":0,"mature_access":"allowed","owners":[{"id":1492423,"first_name":"Ritika","last_name":"Periwal","username":"ritikaperiwal","city":"Delhi","state":"","country":"India","company":"Chaos Design","occupation":"Junior Art Director","created_on":1345309567,"url":"http:\/\/www.behance.net\/ritikaperiwal","images":{"50":"http:\/\/m1.behance.net\/profiles6\/1492423\/50x98ace7f44babffb2cc3a369f81052a90.jpg","115":"http:\/\/m1.behance.net\/profiles6\/1492423\/115x98ace7f44babffb2cc3a369f81052a90.jpg","138":"http:\/\/m1.behance.net\/profiles6\/1492423\/98ace7f44babffb2cc3a369f81052a90.jpg"},"display_name":"Ritika Periwal","fields":["Graphic Design","Art Direction","Branding"]}],"stats":{"views":119,"appreciations":7,"comments":0},"for_sale":0},{"id":8765573,"name":"FOSTER CITY HIGH SCHOOL FOUNDATION","published_on":1388524057,"created_on":1368838869,"modified_on":1388524057,"url":"http:\/\/www.behance.net\/gallery\/FOSTER-CITY-HIGH-SCHOOL-FOUNDATION\/8765573","privacy":"public","fields":["Branding","Graphic Design"],"covers":{"404":"http:\/\/m1.behance.net\/rendition\/projects\/8765573\/404\/481b9116af918f9f1b10c9dadbe1d944.jpg","202":"http:\/\/m1.behance.net\/rendition\/projects\/8765573\/orig\/481b9116af918f9f1b10c9dadbe1d944.jpg","230":"http:\/\/m1.behance.net\/rendition\/projects\/8765573\/230\/481b9116af918f9f1b10c9dadbe1d944.jpg","115":"http:\/\/m1.behance.net\/rendition\/projects\/8765573\/115\/481b9116af918f9f1b10c9dadbe1d944.jpg"},"mature_content":0,"mature_access":"allowed","owners":[{"id":976063,"first_name":"Michelle","last_name":"Vidro","username":"michellevidro","city":"Fairfax","state":"California","country":"United States","company":"","occupation":"Designer: Graphics, Illustration, Jewelry Design","created_on":1330653730,"url":"http:\/\/www.behance.net\/michellevidro","images":{"50":"http:\/\/m1.behance.net\/profiles9\/976063\/50x8523052d522ae3fb219f0fb5091826d5.jpg","115":"http:\/\/m1.behance.net\/profiles9\/976063\/115x8523052d522ae3fb219f0fb5091826d5.jpg","138":"http:\/\/m1.behance.net\/profiles9\/976063\/8523052d522ae3fb219f0fb5091826d5.jpg"},"display_name":"Michelle Vidro","fields":["Graphic Design","Illustration","Branding"]}],"stats":{"views":15,"appreciations":0,"comments":0},"for_sale":0},{"id":3644885,"name":"Creature from Sticker series","published_on":1386246012,"created_on":1334390402,"modified_on":1386246012,"url":"http:\/\/www.behance.net\/gallery\/Creature-from-Sticker-series\/3644885","privacy":"public","fields":["Crafts","Graphic Design","Icon Design"],"covers":{"202":"http:\/\/m1.behance.net\/rendition\/projects\/3644885\/orig\/02fd81f88557ef65123796390e892799.jpg","115":"http:\/\/m1.behance.net\/rendition\/projects\/3644885\/115\/02fd81f88557ef65123796390e892799.jpg"},"mature_content":0,"mature_access":"allowed","owners":[{"id":126569,"first_name":"Yuan","last_name":"Guo","username":"GuoYuan","city":"Shenzhen","state":"","country":"China","company":"","occupation":"Junior Art Director\/Graphic Designer","created_on":1254747092,"url":"http:\/\/www.behance.net\/GuoYuan","images":{"50":"http:\/\/m1.behance.net\/profiles4\/126569\/50xb87f0dd18817eb4bb97b507a94cd1010.jpg","115":"http:\/\/m1.behance.net\/profiles4\/126569\/115xb87f0dd18817eb4bb97b507a94cd1010.jpg","138":"http:\/\/m1.behance.net\/profiles4\/126569\/b87f0dd18817eb4bb97b507a94cd1010.jpg"},"display_name":"Yuan Guo","fields":["Advertising","Illustration","Graphic Design"]}],"stats":{"views":115,"appreciations":1,"comments":0},"for_sale":0},{"id":11100243,"name":"Agnitus - Youtube Video Cover","published_on":1384335099,"created_on":1380056340,"modified_on":1384335099,"url":"http:\/\/www.behance.net\/gallery\/Agnitus-Youtube-Video-Cover\/11100243","privacy":"public","fields":["Game Design","Graphic Design","Web Design"],"covers":{"404":"http:\/\/m1.behance.net\/rendition\/projects\/11100243\/404\/c252942f7f1900576253d6fbfca9df34.png","202":"http:\/\/m1.behance.net\/rendition\/projects\/11100243\/orig\/c252942f7f1900576253d6fbfca9df34.png","230":"http:\/\/m1.behance.net\/rendition\/projects\/11100243\/230\/c252942f7f1900576253d6fbfca9df34.png","115":"http:\/\/m1.behance.net\/rendition\/projects\/11100243\/115\/c252942f7f1900576253d6fbfca9df34.png"},"mature_content":0,"mature_access":"allowed","owners":[{"id":185988,"first_name":"Yasir","last_name":"Wadood","username":"yasirwadood","city":"Islamabad","state":"","country":"Pakistan","company":"","occupation":"UX \/ UI Designer","created_on":1277754933,"url":"http:\/\/www.behance.net\/yasirwadood","images":{"50":"http:\/\/m1.behance.net\/profiles5\/185988\/50x53b32d0690136c79d37ffa1460b6573c.png","115":"http:\/\/m1.behance.net\/profiles5\/185988\/115x53b32d0690136c79d37ffa1460b6573c.png","138":"http:\/\/m1.behance.net\/profiles5\/185988\/53b32d0690136c79d37ffa1460b6573c.png"},"display_name":"Yasir Wadood","fields":["Graphic Design","UI\/UX","Web Design"]},{"id":1664319,"first_name":"Ahmed","last_name":"Hassan","username":"me2ahmedhassan","city":"Islamabad","state":"","country":"Pakistan","company":"Agnitus","occupation":"Web Designer","created_on":1349268089,"url":"http:\/\/www.behance.net\/me2ahmedhassan","images":{"50":"http:\/\/m1.behance.net\/profiles16\/1664319\/50x87bc1e840bd70197cd922e6f20904a4e.jpg","115":"http:\/\/m1.behance.net\/profiles16\/1664319\/115x87bc1e840bd70197cd922e6f20904a4e.jpg","138":"http:\/\/m1.behance.net\/profiles16\/1664319\/87bc1e840bd70197cd922e6f20904a4e.jpg"},"display_name":"Ahmed Hassan","fields":["UI\/UX","Web Design","Web Development"]}],"stats":{"views":606,"appreciations":73,"comments":2},"for_sale":0},{"id":3267681,"name":"Illustration Methodologies","published_on":1383536378,"created_on":1330537684,"modified_on":1384370986,"url":"http:\/\/www.behance.net\/gallery\/Illustration-Methodologies\/3267681","privacy":"public","fields":["Digital Art","Graphic Design","Illustration"],"covers":{"404":"http:\/\/m1.behance.net\/rendition\/projects\/3267681\/404\/8fefabc320ed7e6a1077fab2437ca4b3.jpeg","202":"http:\/\/m1.behance.net\/rendition\/projects\/3267681\/orig\/8fefabc320ed7e6a1077fab2437ca4b3.jpeg","230":"http:\/\/m1.behance.net\/rendition\/projects\/3267681\/230\/8fefabc320ed7e6a1077fab2437ca4b3.jpeg","115":"http:\/\/m1.behance.net\/rendition\/projects\/3267681\/115\/8fefabc320ed7e6a1077fab2437ca4b3.jpeg"},"mature_content":0,"mature_access":"allowed","owners":[{"id":303287,"first_name":"Rory","last_name":"Tatton","username":"RiDT","city":"Camberley","state":"","country":"United Kingdom","company":"","occupation":"","created_on":1296086737,"url":"http:\/\/www.behance.net\/RiDT","images":{"50":"http:\/\/m1.behance.net\/profiles16\/303287\/50xbc474fae5d178e9c67fc01b874d63620.jpg","115":"http:\/\/m1.behance.net\/profiles16\/303287\/115xbc474fae5d178e9c67fc01b874d63620.jpg","138":"http:\/\/m1.behance.net\/profiles16\/303287\/bc474fae5d178e9c67fc01b874d63620.jpg"},"display_name":"Rory Tatton","fields":["Graphic Design","Illustration","Print Design"]}],"stats":{"views":72,"appreciations":4,"comments":1},"for_sale":0},{"id":2491689,"name":"Central Park Zoo","published_on":1383371947,"created_on":1321149523,"modified_on":1389221144,"url":"http:\/\/www.behance.net\/gallery\/Central-Park-Zoo\/2491689","privacy":"public","fields":["Graphic Design","Branding"],"covers":{"404":"http:\/\/m1.behance.net\/rendition\/projects\/2491689\/404\/a7a28664723a582769ce6c4b7f45d615.","202":"http:\/\/m1.behance.net\/rendition\/projects\/2491689\/orig\/a7a28664723a582769ce6c4b7f45d615.","230":"http:\/\/m1.behance.net\/rendition\/projects\/2491689\/230\/a7a28664723a582769ce6c4b7f45d615.","115":"http:\/\/m1.behance.net\/rendition\/projects\/2491689\/115\/a7a28664723a582769ce6c4b7f45d615."},"mature_content":0,"mature_access":"allowed","owners":[{"id":102684,"first_name":"Jane","last_name":"Gardner","username":"janegardner","city":"New York","state":"New York","country":"United States","company":"","occupation":"Graphic Designer","created_on":1241038998,"url":"http:\/\/www.behance.net\/janegardner","images":{"50":"http:\/\/m1.behance.net\/profiles5\/102684\/50x14823e0620bb8782c74c0f3995f33a36.jpg","115":"http:\/\/m1.behance.net\/profiles5\/102684\/115x14823e0620bb8782c74c0f3995f33a36.jpg","138":"http:\/\/m1.behance.net\/profiles5\/102684\/14823e0620bb8782c74c0f3995f33a36.jpg"},"display_name":"Jane Gardner","fields":["Graphic Design","Illustration","Print Design"]}],"stats":{"views":827,"appreciations":8,"comments":0},"for_sale":0},{"id":11565137,"name":"Touch Me","published_on":1382105341,"created_on":1382105049,"modified_on":1382105341,"url":"http:\/\/www.behance.net\/gallery\/Touch-Me\/11565137","privacy":"public","fields":["Digital Art","Graphic Design","Visual Effects"],"covers":{"404":"http:\/\/m1.behance.net\/rendition\/projects\/11565137\/404\/b7e390d569a86cf7bfd887ff342c059f.jpeg","202":"http:\/\/m1.behance.net\/rendition\/projects\/11565137\/orig\/b7e390d569a86cf7bfd887ff342c059f.jpeg","230":"http:\/\/m1.behance.net\/rendition\/projects\/11565137\/230\/b7e390d569a86cf7bfd887ff342c059f.jpeg","115":"http:\/\/m1.behance.net\/rendition\/projects\/11565137\/115\/b7e390d569a86cf7bfd887ff342c059f.jpeg"},"mature_content":0,"mature_access":"allowed","owners":[{"id":2164665,"first_name":"rash","last_name":"shop","username":"cristina_lobo","city":"Granada","state":"","country":"Spain","company":"","occupation":"Creative Designer","created_on":1359892172,"url":"http:\/\/www.behance.net\/cristina_lobo","images":{"50":"http:\/\/m1.behance.net\/profiles6\/2164665\/50x36e9427d4c26204ffc23089c14a83862.jpg","115":"http:\/\/m1.behance.net\/profiles6\/2164665\/115x36e9427d4c26204ffc23089c14a83862.jpg","138":"http:\/\/m1.behance.net\/profiles6\/2164665\/36e9427d4c26204ffc23089c14a83862.jpg"},"display_name":"rash shop","fields":["Fashion","Graphic Design","Interior Design"]}],"stats":{"views":68,"appreciations":10,"comments":2},"for_sale":0},{"id":11504885,"name":"Dancing School Poster","published_on":1381950119,"created_on":1381867925,"modified_on":1382128276,"url":"http:\/\/www.behance.net\/gallery\/Dancing-School-Poster\/11504885","privacy":"public","fields":["Art Direction","Graphic Design","Print Design"],"covers":{"404":"http:\/\/m1.behance.net\/rendition\/projects\/11504885\/404\/781a400ee6dfbff3f2e701bc7102fb10.jpeg","202":"http:\/\/m1.behance.net\/rendition\/projects\/11504885\/orig\/781a400ee6dfbff3f2e701bc7102fb10.jpeg","230":"http:\/\/m1.behance.net\/rendition\/projects\/11504885\/230\/781a400ee6dfbff3f2e701bc7102fb10.jpeg","115":"http:\/\/m1.behance.net\/rendition\/projects\/11504885\/115\/781a400ee6dfbff3f2e701bc7102fb10.jpeg"},"mature_content":0,"mature_access":"allowed","owners":[{"id":3742905,"first_name":"Anton","last_name":"Rozhin","username":"uglyfaced","city":"Yekaterinburg","state":"","country":"Russian Federation","company":"\"Voskhod\" Advertising Agency","occupation":"Copywriter","created_on":1381320130,"url":"http:\/\/www.behance.net\/uglyfaced","images":{"50":"http:\/\/m1.behance.net\/profiles21\/3742905\/50x31b2722dd1360a0936fd74b36a007627.jpg","115":"http:\/\/m1.behance.net\/profiles21\/3742905\/115x31b2722dd1360a0936fd74b36a007627.jpg","138":"http:\/\/m1.behance.net\/profiles21\/3742905\/31b2722dd1360a0936fd74b36a007627.jpg"},"display_name":"Anton Rozhin","fields":["Graphic Design","Art Direction","Print Design"]}],"stats":{"views":62,"appreciations":1,"comments":0},"for_sale":0},{"id":11523923,"name":"Design Future","published_on":1381943330,"created_on":1381943268,"modified_on":1382005380,"url":"http:\/\/www.behance.net\/gallery\/Design-Future\/11523923","privacy":"public","fields":["Advertising","Branding","Graphic Design"],"covers":{"404":"http:\/\/m1.behance.net\/rendition\/projects\/11523923\/404\/8f5b14ece45f39e7ca3f55ec301faa22.png","202":"http:\/\/m1.behance.net\/rendition\/projects\/11523923\/orig\/8f5b14ece45f39e7ca3f55ec301faa22.png","230":"http:\/\/m1.behance.net\/rendition\/projects\/11523923\/230\/8f5b14ece45f39e7ca3f55ec301faa22.png","115":"http:\/\/m1.behance.net\/rendition\/projects\/11523923\/115\/8f5b14ece45f39e7ca3f55ec301faa22.png"},"mature_content":0,"mature_access":"allowed","owners":[{"id":3813595,"first_name":"Nick","last_name":"Nastich","username":"nastich","city":"Moscow","state":"","country":"Russian Federation","company":"","occupation":"Branding, Packaging, UX\/UI","created_on":1381829822,"url":"http:\/\/www.behance.net\/nastich","images":{"50":"http:\/\/m1.behance.net\/profiles19\/3813595\/50xdccc74059bb614ceb0dcff8001096e1e.png","115":"http:\/\/m1.behance.net\/profiles19\/3813595\/115xdccc74059bb614ceb0dcff8001096e1e.png","138":"http:\/\/m1.behance.net\/profiles19\/3813595\/dccc74059bb614ceb0dcff8001096e1e.png"},"display_name":"Nick Nastich","fields":["Graphic Design","Branding","Advertising"]}],"stats":{"views":78,"appreciations":8,"comments":1},"for_sale":0},{"id":11515849,"name":"SSgA book","published_on":1381917275,"created_on":1381917089,"modified_on":1381917275,"url":"http:\/\/www.behance.net\/gallery\/SSgA-book\/11515849","privacy":"public","fields":["Art Direction","Creative Direction","Graphic Design"],"covers":{"404":"http:\/\/m1.behance.net\/rendition\/projects\/11515849\/404\/138d446c422439842e22eed28ab2d361.jpeg","202":"http:\/\/m1.behance.net\/rendition\/projects\/11515849\/orig\/138d446c422439842e22eed28ab2d361.jpeg","230":"http:\/\/m1.behance.net\/rendition\/projects\/11515849\/230\/138d446c422439842e22eed28ab2d361.jpeg","115":"http:\/\/m1.behance.net\/rendition\/projects\/11515849\/115\/138d446c422439842e22eed28ab2d361.jpeg"},"mature_content":0,"mature_access":"allowed","owners":[{"id":592571,"first_name":"gie","last_name":"maggie","username":"giemaggie","city":"Houston","state":"Texas","country":"United States","company":"","occupation":"Bachelor Degree","created_on":1313569343,"url":"http:\/\/www.behance.net\/giemaggie","images":{"50":"http:\/\/m1.behance.net\/profiles10\/592571\/50xb5701aea7d107bc80d194b8ab6f9fdea.jpg","115":"http:\/\/m1.behance.net\/profiles10\/592571\/115xb5701aea7d107bc80d194b8ab6f9fdea.jpg","138":"http:\/\/m1.behance.net\/profiles10\/592571\/b5701aea7d107bc80d194b8ab6f9fdea.jpg"},"display_name":"gie maggie","fields":["Graphic Design","Print Design","Creative Direction"]}],"stats":{"views":55,"appreciations":0,"comments":0},"for_sale":0},{"id":11504585,"name":"Sistema de identidad","published_on":1381867196,"created_on":1381867087,"modified_on":1381867196,"url":"http:\/\/www.behance.net\/gallery\/Sistema-de-identidad\/11504585","privacy":"public","fields":["Branding","Graphic Design"],"covers":{"404":"http:\/\/m1.behance.net\/rendition\/projects\/11504585\/404\/3d0e79fde40cbb076d46f073e7a305e7.jpeg","202":"http:\/\/m1.behance.net\/rendition\/projects\/11504585\/orig\/3d0e79fde40cbb076d46f073e7a305e7.jpeg","230":"http:\/\/m1.behance.net\/rendition\/projects\/11504585\/230\/3d0e79fde40cbb076d46f073e7a305e7.jpeg","115":"http:\/\/m1.behance.net\/rendition\/projects\/11504585\/115\/3d0e79fde40cbb076d46f073e7a305e7.jpeg"},"mature_content":0,"mature_access":"allowed","owners":[{"id":488635,"first_name":"Eliana","last_name":"Tyszberowicz","username":"elutyszbe","city":"Buenos Aires","state":"","country":"Argentina","company":"","occupation":"Graphic designer","created_on":1307489077,"url":"http:\/\/www.behance.net\/elutyszbe","images":{"50":"http:\/\/m1.behance.net\/profiles25\/488635\/50x8f387ae9da730abe60d05b4ed356e5f1.jpg","115":"http:\/\/m1.behance.net\/profiles25\/488635\/115x8f387ae9da730abe60d05b4ed356e5f1.jpg","138":"http:\/\/m1.behance.net\/profiles25\/488635\/8f387ae9da730abe60d05b4ed356e5f1.jpg"},"display_name":"Eliana Tyszberowicz","fields":["Graphic Design","Editorial Design","Web Design"]}],"stats":{"views":11,"appreciations":0,"comments":0},"for_sale":0}],"http_code":200}