{"projects":[{"id":2825429,"name":"Eco-Me","published_on":1326057780,"created_on":1326057633,"modified_on":1353465081,"url":"http:\/\/www.behance.net\/gallery\/Eco-Me\/2825429","privacy":"public","fields":["Art Direction","Branding","Graphic Design"],"covers":{"202":"http:\/\/m1.behance.net\/rendition\/projects\/2825429\/orig\/0b8f2c9498c60d57c7a543bbbc2dd720.jpg","115":"http:\/\/m1.behance.net\/rendition\/projects\/2825429\/115\/0b8f2c9498c60d57c7a543bbbc2dd720.jpg"},"mature_content":0,"mature_access":"allowed","owners":[{"id":245784,"first_name":"Tattfoo Design","last_name":"","username":"tattfoodesign","city":"City","state":"New York","country":"United States","location":"NY, USA","company":"","occupation":"Founder","created_on":1287312203,"url":"http:\/\/www.behance.net\/tattfoodesign","images":{"50":"http:\/\/m1.behance.net\/profiles4\/245784\/50xad92ec54fdf6101840dad8f9d26674ca.jpg","115":"http:\/\/m1.behance.net\/profiles4\/245784\/115xad92ec54fdf6101840dad8f9d26674ca.jpg","138":"http:\/\/m1.behance.net\/profiles4\/245784\/ad92ec54fdf6101840dad8f9d26674ca.jpg"},"display_name":"Tattfoo Design","fields":["Graphic Design","Branding","Advertising"]}],"stats":{"views":70,"appreciations":1,"comments":0},"for_sale":0},{"id":2831659,"name":"Cocoon at Cocoric\u00f2 posters","published_on":1326126924,"created_on":1326126646,"modified_on":1353465439,"url":"http:\/\/www.behance.net\/gallery\/Cocoon-at-Cocorico-posters\/2831659","privacy":"public","fields":["Graphic Design"],"covers":{"202":"http:\/\/m1.behance.net\/rendition\/projects\/2831659\/orig\/1d8c690d95dc828f628347c30503fe73.jpg","115":"http:\/\/m1.behance.net\/rendition\/projects\/2831659\/115\/1d8c690d95dc828f628347c30503fe73.jpg"},"mature_content":0,"mature_access":"allowed","owners":[{"id":263872,"first_name":"Luca","last_name":"Masini","username":"lucamasini","city":"Pisa","state":"","country":"Italy","location":"Pisa, Italy","company":"zerouno","occupation":"","created_on":1290017216,"url":"http:\/\/www.behance.net\/lucamasini","images":{"50":"http:\/\/m1.behance.net\/profiles20\/263872\/50xc0ca515f63f76515ce3af50d4018e14e.jpg","115":"http:\/\/m1.behance.net\/profiles20\/263872\/115xc0ca515f63f76515ce3af50d4018e14e.jpg","138":"http:\/\/m1.behance.net\/profiles20\/263872\/c0ca515f63f76515ce3af50d4018e14e.jpg"},"display_name":"Luca Masini","fields":["Graphic Design","Print Design","Web Design"]}],"stats":{"views":98,"appreciations":0,"comments":0},"for_sale":0},{"id":2834445,"name":"Digital Maps of India","published_on":1326148157,"created_on":1326147437,"modified_on":1353465596,"url":"http:\/\/www.behance.net\/gallery\/Digital-Maps-of-India\/2834445","privacy":"public","fields":["Advertising","Digital Art","Graphic Design"],"covers":{"202":"http:\/\/m1.behance.net\/rendition\/projects\/2834445\/orig\/1dc10f219f52ebb7088027d99caed2ef.jpg","115":"http:\/\/m1.behance.net\/rendition\/projects\/2834445\/115\/1dc10f219f52ebb7088027d99caed2ef.jpg"},"mature_content":0,"mature_access":"allowed","owners":[{"id":519019,"first_name":"Neha","last_name":"Verman","username":"nehav","city":"Mississauga","state":"Ontario","country":"Canada","location":"Mississauga, Ontario, Canada","company":"Dezignflow","occupation":"Graphic Designer","created_on":1309317509,"url":"http:\/\/www.behance.net\/nehav","images":{"50":"http:\/\/m1.behance.net\/profiles13\/519019\/50x4002157e684f3feddad0dce1763e9f44.jpg","115":"http:\/\/m1.behance.net\/profiles13\/519019\/115x4002157e684f3feddad0dce1763e9f44.jpg","138":"http:\/\/m1.behance.net\/profiles13\/519019\/4002157e684f3feddad0dce1763e9f44.jpg"},"display_name":"Neha Verman","fields":["Graphic Design","Advertising","Print Design"]}],"stats":{"views":55,"appreciations":1,"comments":0},"for_sale":0},{"id":2836171,"name":"typo","published_on":1326163851,"created_on":1326163185,"modified_on":1353465688,"url":"http:\/\/www.behance.net\/gallery\/typo\/2836171","privacy":"public","fields":["Graphic Design","Philosophy","Typography"],"covers":{"202":"http:\/\/m1.behance.net\/rendition\/projects\/2836171\/orig\/99d914b8206445cdf72df863eb9e5a10.jpg","115":"http:\/\/m1.behance.net\/rendition\/projects\/2836171\/115\/99d914b8206445cdf72df863eb9e5a10.jpg"},"mature_content":0,"mature_access":"allowed","owners":[{"id":179376,"first_name":"arief","last_name":"ARF","username":"arfarf","city":"Jakarta","state":"","country":"Indonesia","location":"Jakarta, Indonesia","company":"groar","occupation":"illustrator & senior graphic designer","created_on":1276739919,"url":"http:\/\/www.behance.net\/arfarf","images":{"50":"http:\/\/m1.behance.net\/profiles5\/179376\/50x276d12c9720b2066025a51f7bfc12922.jpg","115":"http:\/\/m1.behance.net\/profiles5\/179376\/115x276d12c9720b2066025a51f7bfc12922.jpg","138":"http:\/\/m1.behance.net\/profiles5\/179376\/276d12c9720b2066025a51f7bfc12922.jpg"},"display_name":"arief ARF","fields":["Graphic Design","Illustration","Branding"]}],"stats":{"views":43,"appreciations":1,"comments":0},"for_sale":1},{"id":2837303,"name":"The Alcohol Project","published_on":1326182033,"created_on":1326180614,"modified_on":1353465748,"url":"http:\/\/www.behance.net\/gallery\/The-Alcohol-Project\/2837303","privacy":"public","fields":["Graphic Design","Illustration","Storytelling"],"covers":{"202":"http:\/\/m1.behance.net\/rendition\/projects\/2837303\/orig\/f72bf9351e89b77f598613db3ff7966a.jpg","115":"http:\/\/m1.behance.net\/rendition\/projects\/2837303\/115\/f72bf9351e89b77f598613db3ff7966a.jpg"},"mature_content":0,"mature_access":"allowed","owners":[{"id":847357,"first_name":"WishBox Studio","last_name":"","username":"wishboxstudio","city":"New Delhi","state":"","country":"India","location":"New Delhi, India","company":"Communication Design and PR","occupation":"Founder and Creative Director","created_on":1326113600,"url":"http:\/\/www.behance.net\/wishboxstudio","images":{"50":"http:\/\/m1.behance.net\/profiles18\/847357\/50xcb48f2634a9c082e6d8974aa13a37947.png","115":"http:\/\/m1.behance.net\/profiles18\/847357\/115xcb48f2634a9c082e6d8974aa13a37947.png","138":"http:\/\/m1.behance.net\/profiles18\/847357\/cb48f2634a9c082e6d8974aa13a37947.png"},"display_name":"WishBox Studio","fields":["Graphic Design","Illustration","Print Design"]}],"stats":{"views":98,"appreciations":3,"comments":1},"for_sale":0},{"id":2858339,"name":"Canon Euro 2012 Save The Date","published_on":1326382156,"created_on":1326381751,"modified_on":1353467046,"url":"http:\/\/www.behance.net\/gallery\/Canon-Euro-2012-Save-The-Date\/2858339","privacy":"public","fields":["Art Direction","Graphic Design","Photo Manipulation"],"covers":{"202":"http:\/\/m1.behance.net\/rendition\/projects\/2858339\/orig\/e62789a6739dbbf01b215cadfb687e90.jpg","115":"http:\/\/m1.behance.net\/rendition\/projects\/2858339\/115\/e62789a6739dbbf01b215cadfb687e90.jpg"},"mature_content":0,"mature_access":"allowed","owners":[{"id":95641,"first_name":"Pietro","last_name":"Gregorini","username":"pietrogregorini","city":"Milan","state":"","country":"Italy","location":"Milan, Italy","company":"","occupation":"Art Director","created_on":1235407213,"url":"http:\/\/www.behance.net\/pietrogregorini","images":{"50":"http:\/\/m1.behance.net\/profiles3\/95641\/50xb9c950e3e0d49cd481c1fb77a00f80c9.jpg","115":"http:\/\/m1.behance.net\/profiles3\/95641\/115xb9c950e3e0d49cd481c1fb77a00f80c9.jpg","138":"http:\/\/m1.behance.net\/profiles3\/95641\/b9c950e3e0d49cd481c1fb77a00f80c9.jpg"},"display_name":"Pietro Gregorini","fields":["Art Direction","Graphic Design","Photo Manipulation"]}],"stats":{"views":533,"appreciations":4,"comments":0},"for_sale":0},{"id":2859293,"name":"Package Design Dina Tea","published_on":1326386500,"created_on":1326385372,"modified_on":1354654684,"url":"http:\/\/www.behance.net\/gallery\/Package-Design-Dina-Tea\/2859293","privacy":"public","fields":["Graphic Design","Packaging","Product Design"],"covers":{"202":"http:\/\/m1.behance.net\/rendition\/projects\/2859293\/orig\/9c101ddac44ce55499ed59d78ec0f893.jpg","115":"http:\/\/m1.behance.net\/rendition\/projects\/2859293\/115\/9c101ddac44ce55499ed59d78ec0f893.jpg"},"mature_content":0,"mature_access":"allowed","owners":[{"id":591907,"first_name":"Hans-J\u00f8rgen","last_name":"L\u00f8ken","username":"loken","city":"Oslo","state":"","country":"Norway","location":"Oslo, Norway","company":"","occupation":"Student","created_on":1313527844,"url":"http:\/\/www.behance.net\/loken","images":{"50":"http:\/\/m1.behance.net\/profiles22\/591907\/50x3957eb15c0e054ae2362a3990ac288ef.jpg","115":"http:\/\/m1.behance.net\/profiles22\/591907\/115x3957eb15c0e054ae2362a3990ac288ef.jpg","138":"http:\/\/m1.behance.net\/profiles22\/591907\/3957eb15c0e054ae2362a3990ac288ef.jpg"},"display_name":"Hans-J\u00f8rgen L\u00f8ken","fields":["Graphic Design","Packaging","Art Direction"]}],"stats":{"views":634,"appreciations":37,"comments":5},"for_sale":0},{"id":2875165,"name":"CDibujos","published_on":1326489783,"created_on":1326486352,"modified_on":1354654713,"url":"http:\/\/www.behance.net\/gallery\/CDibujos\/2875165","privacy":"public","fields":["Digital Art","Graphic Design","Illustration"],"covers":{"115":"http:\/\/a2.behance.net\/img\/\/covers\/115-blocked.png","202":"http:\/\/a2.behance.net\/img\/\/covers\/202-blocked.png"},"mature_content":1,"mature_access":"logged-out","owners":[{"id":859119,"first_name":"Joa","last_name":"Aldana","username":"joaldana","city":"City","state":"","country":"Venezuela","location":"Venezuela","company":"","occupation":"Graphic Design","created_on":1326485770,"url":"http:\/\/www.behance.net\/joaldana","images":{"50":"http:\/\/m1.behance.net\/profiles12\/859119\/50x931eff1d06704dcadae30157655bfb7f.jpg","115":"http:\/\/m1.behance.net\/profiles12\/859119\/115x931eff1d06704dcadae30157655bfb7f.jpg","138":"http:\/\/m1.behance.net\/profiles12\/859119\/931eff1d06704dcadae30157655bfb7f.jpg"},"display_name":"Joa Aldana","fields":["Digital Art","Illustration","Graphic Design"]}],"stats":{"views":56,"appreciations":9,"comments":0},"for_sale":0},{"id":2878909,"name":"Logotipo Escuela Infantil","published_on":1326645950,"created_on":1326542940,"modified_on":1354180701,"url":"http:\/\/www.behance.net\/gallery\/Logotipo-Escuela-Infantil\/2878909","privacy":"public","fields":["Design","Graphic Design","Industrial Design"],"covers":{"202":"http:\/\/m1.behance.net\/rendition\/projects\/2878909\/orig\/9e8ae271d0da70a22ec7a0ca99210f26.jpg","115":"http:\/\/m1.behance.net\/rendition\/projects\/2878909\/115\/9e8ae271d0da70a22ec7a0ca99210f26.jpg"},"mature_content":0,"mature_access":"allowed","owners":[{"id":860161,"first_name":"Salvador","last_name":"Enguidanos Contel","username":"salengui","city":"Valencia","state":"","country":"Spain","location":"Valencia, Spain","company":"","occupation":"Dise\u00f1ador Industrial y Grafico","created_on":1326542568,"url":"http:\/\/www.behance.net\/salengui","images":{"50":"http:\/\/a2.behance.net\/img\/profile\/no-image-50.jpg?cb=485136376","115":"http:\/\/a2.behance.net\/img\/profile\/no-image-115.jpg?cb=485136376","138":"http:\/\/a2.behance.net\/img\/profile\/no-image-138.jpg?cb=485136376"},"display_name":"Salvador Enguidanos Contel","fields":["Graphic Design","Illustration","Design"]}],"stats":{"views":92,"appreciations":0,"comments":0},"for_sale":1},{"id":2885103,"name":"Logo design","published_on":1326625800,"created_on":1326625083,"modified_on":1353468620,"url":"http:\/\/www.behance.net\/gallery\/Logo-design\/2885103","privacy":"public","fields":["Design","Drawing","Graphic Design"],"covers":{"202":"http:\/\/m1.behance.net\/rendition\/projects\/2885103\/orig\/73f990cb843c7002d44e7819aa532777.jpg","115":"http:\/\/m1.behance.net\/rendition\/projects\/2885103\/115\/73f990cb843c7002d44e7819aa532777.jpg"},"mature_content":0,"mature_access":"allowed","owners":[{"id":82272,"first_name":"Rajendra","last_name":"ray","username":"rajeray","city":"Hyderabad","state":"","country":"India","location":"Hyderabad, India","company":"mouse n brush","occupation":"Designer","created_on":1222219536,"url":"http:\/\/www.behance.net\/rajeray","images":{"50":"http:\/\/m1.behance.net\/profiles\/82272\/50x0e78693b3d0dfc48e26f52c6557fb610.jpg","115":"http:\/\/m1.behance.net\/profiles\/82272\/115x0e78693b3d0dfc48e26f52c6557fb610.jpg","138":"http:\/\/m1.behance.net\/profiles\/82272\/0e78693b3d0dfc48e26f52c6557fb610.jpg"},"display_name":"Rajendra ray","fields":["Graphic Design","Web Design","Branding"]}],"stats":{"views":56,"appreciations":3,"comments":0},"for_sale":1},{"id":2887587,"name":"The old plate","published_on":1326655002,"created_on":1326654394,"modified_on":1353468771,"url":"http:\/\/www.behance.net\/gallery\/The-old-plate\/2887587","privacy":"public","fields":["Graphic Design"],"covers":{"202":"http:\/\/m1.behance.net\/rendition\/projects\/2887587\/orig\/3e86f5117d0e83671ede1a175da34967.jpg","115":"http:\/\/m1.behance.net\/rendition\/projects\/2887587\/115\/3e86f5117d0e83671ede1a175da34967.jpg"},"mature_content":0,"mature_access":"allowed","owners":[{"id":862229,"first_name":"francois","last_name":"minery","username":"fabrikmobile","city":"City","state":"","country":"France","location":"France","company":"","occupation":"creative something","created_on":1326651477,"url":"http:\/\/www.behance.net\/fabrikmobile","images":{"50":"http:\/\/m1.behance.net\/profiles11\/862229\/50xf2fe9f1958b8057efb5a45b990f19827.jpg","115":"http:\/\/m1.behance.net\/profiles11\/862229\/115xf2fe9f1958b8057efb5a45b990f19827.jpg","138":"http:\/\/m1.behance.net\/profiles11\/862229\/f2fe9f1958b8057efb5a45b990f19827.jpg"},"display_name":"francois minery","fields":["Graphic Design"]}],"stats":{"views":17,"appreciations":0,"comments":0},"for_sale":0},{"id":2889193,"name":"Johns Hopkins University Inter-Asian Council 2009-2011","published_on":1326667409,"created_on":1326666620,"modified_on":1361656245,"url":"http:\/\/www.behance.net\/gallery\/Johns-Hopkins-University-Inter-Asian-Council-2009-2011\/2889193","privacy":"public","fields":["Graphic Design"],"covers":{"202":"http:\/\/m1.behance.net\/rendition\/projects\/2889193\/orig\/4258d3d0d1fd8a9f761881bc3b2ab866.jpg","115":"http:\/\/m1.behance.net\/rendition\/projects\/2889193\/115\/4258d3d0d1fd8a9f761881bc3b2ab866.jpg"},"mature_content":0,"mature_access":"allowed","owners":[{"id":452547,"first_name":"Karen","last_name":"Chan","username":"kschan","city":"Silver Spring","state":"Maryland","country":"United States","location":"Silver Spring, MD, USA","company":"","occupation":"","created_on":1305407823,"url":"http:\/\/www.behance.net\/kschan","images":{"50":"http:\/\/m1.behance.net\/profiles25\/452547\/50xa23debc6d3d0244187ae6434ef66e957.jpg","115":"http:\/\/m1.behance.net\/profiles25\/452547\/115xa23debc6d3d0244187ae6434ef66e957.jpg","138":"http:\/\/m1.behance.net\/profiles25\/452547\/a23debc6d3d0244187ae6434ef66e957.jpg"},"display_name":"Karen Chan","fields":["Graphic Design","Painting"]}],"stats":{"views":25,"appreciations":0,"comments":0},"for_sale":0}],"http_code":200}