{"projects":[{"id":8113625,"name":"Logos 2013 (1)","published_on":1365718530,"created_on":1365717535,"modified_on":1365718530,"url":"http:\/\/www.behance.net\/gallery\/Logos-2013-(1)\/8113625","privacy":"public","fields":["Art Direction","Branding","Graphic Design"],"covers":{"404":"http:\/\/m1.behance.net\/rendition\/projects\/8113625\/404\/b2cce75a1d41d12510534eb9c6926985.jpg","202":"http:\/\/m1.behance.net\/rendition\/projects\/8113625\/orig\/b2cce75a1d41d12510534eb9c6926985.jpg","230":"http:\/\/m1.behance.net\/rendition\/projects\/8113625\/230\/b2cce75a1d41d12510534eb9c6926985.jpg","115":"http:\/\/m1.behance.net\/rendition\/projects\/8113625\/115\/b2cce75a1d41d12510534eb9c6926985.jpg"},"mature_content":0,"mature_access":"allowed","owners":[{"id":113427,"first_name":"Julien","last_name":"Ombede Ohandja","username":"Ombede","city":"Yaounde","state":"","country":"Cameroon","company":"","occupation":"Multimedia","created_on":1247161676,"url":"http:\/\/www.behance.net\/Ombede","images":{"50":"http:\/\/m1.behance.net\/profiles2\/113427\/50x5d16dae249b2502393f3662150c3c00a.jpg","115":"http:\/\/m1.behance.net\/profiles2\/113427\/115x5d16dae249b2502393f3662150c3c00a.jpg","138":"http:\/\/m1.behance.net\/profiles2\/113427\/5d16dae249b2502393f3662150c3c00a.jpg"},"display_name":"Julien Ombede Ohandja","fields":["Graphic Design","Branding","Photo Manipulation"]}],"stats":{"views":1469,"appreciations":109,"comments":5},"for_sale":0},{"id":815278,"name":"T-Shirts Designs (2008-2010)","published_on":1290026223,"created_on":1290025719,"modified_on":1392210687,"url":"http:\/\/www.behance.net\/gallery\/T-Shirts-Designs-(2008-2010)\/815278","privacy":"public","fields":["Fashion","Graphic Design","Textile Design"],"covers":{"202":"http:\/\/m1.behance.net\/rendition\/projects\/815278\/orig\/3835acb05b2a03abef90641d23fbcf6c.jpg","115":"http:\/\/m1.behance.net\/rendition\/projects\/815278\/115\/3835acb05b2a03abef90641d23fbcf6c.jpg"},"mature_content":0,"mature_access":"allowed","owners":[{"id":263981,"first_name":"Benjamin","last_name":"Cann","username":"Gengis","city":"Karlsruhe","state":"","country":"Germany","company":"","occupation":"Art, Design & Photography","created_on":1290020671,"url":"http:\/\/www.behance.net\/Gengis","images":{"50":"http:\/\/m1.behance.net\/profiles16\/263981\/50xfd3c236a600f77b47ae309c710235feb.","115":"http:\/\/m1.behance.net\/profiles16\/263981\/115xfd3c236a600f77b47ae309c710235feb.","138":"http:\/\/m1.behance.net\/profiles16\/263981\/fd3c236a600f77b47ae309c710235feb."},"display_name":"Benjamin Cann","fields":["Product Design","Photography","Fashion"]}],"stats":{"views":879,"appreciations":12,"comments":2},"for_sale":1},{"id":8167811,"name":"ALSHARQIYA  Advertising  |  identity & website","published_on":1366034773,"created_on":1366031581,"modified_on":1373890465,"url":"http:\/\/www.behance.net\/gallery\/ALSHARQIYA-Advertising-identity-website\/8167811","privacy":"public","fields":["Branding","Graphic Design","Web Design"],"covers":{"404":"http:\/\/m1.behance.net\/rendition\/projects\/8167811\/404\/a17b2a0a440f3aedf0a1a842ea074d3d.jpg","202":"http:\/\/m1.behance.net\/rendition\/projects\/8167811\/orig\/a17b2a0a440f3aedf0a1a842ea074d3d.jpg","230":"http:\/\/m1.behance.net\/rendition\/projects\/8167811\/230\/a17b2a0a440f3aedf0a1a842ea074d3d.jpg","115":"http:\/\/m1.behance.net\/rendition\/projects\/8167811\/115\/a17b2a0a440f3aedf0a1a842ea074d3d.jpg"},"mature_content":0,"mature_access":"allowed","owners":[{"id":1303723,"first_name":"Mahmoud","last_name":"Elhosary","username":"elhosary","city":"Al Khobar","state":"","country":"Saudi Arabia","company":"","occupation":"Senior Graphic & Web Designer","created_on":1341218432,"url":"http:\/\/www.behance.net\/elhosary","images":{"50":"http:\/\/m1.behance.net\/profiles17\/1303723\/50x8d98f9a377be57c2e6ca723486da3dd7.png","115":"http:\/\/m1.behance.net\/profiles17\/1303723\/115x8d98f9a377be57c2e6ca723486da3dd7.png","138":"http:\/\/m1.behance.net\/profiles17\/1303723\/8d98f9a377be57c2e6ca723486da3dd7.png"},"display_name":"Mahmoud Elhosary","fields":["Advertising","Graphic Design","Art Direction"]}],"stats":{"views":598,"appreciations":30,"comments":21},"for_sale":0},{"id":9020375,"name":"BaseballFesta in Fukushima logo","published_on":1369909017,"created_on":1369908925,"modified_on":1392122643,"url":"http:\/\/www.behance.net\/gallery\/BaseballFesta-in-Fukushima-logo\/9020375","privacy":"public","fields":["Art Direction","Branding","Graphic Design"],"covers":{"404":"http:\/\/m1.behance.net\/rendition\/projects\/9020375\/404\/67c186f201cd30a97c2c18580f738182.jpeg","202":"http:\/\/m1.behance.net\/rendition\/projects\/9020375\/orig\/67c186f201cd30a97c2c18580f738182.jpeg","230":"http:\/\/m1.behance.net\/rendition\/projects\/9020375\/230\/67c186f201cd30a97c2c18580f738182.jpeg","115":"http:\/\/m1.behance.net\/rendition\/projects\/9020375\/115\/67c186f201cd30a97c2c18580f738182.jpeg"},"mature_content":0,"mature_access":"allowed","owners":[{"id":2743223,"first_name":"masaomi","last_name":"fujita","username":"tegusu","city":"Tokyo","state":"","country":"Japan","company":"tegusu","occupation":"Art Director","created_on":1369104115,"url":"http:\/\/www.behance.net\/tegusu","images":{"50":"http:\/\/m1.behance.net\/profiles24\/2743223\/50x74a6574c07d5341eb52b27ce766c1086.jpg","115":"http:\/\/m1.behance.net\/profiles24\/2743223\/115x74a6574c07d5341eb52b27ce766c1086.jpg","138":"http:\/\/m1.behance.net\/profiles24\/2743223\/74a6574c07d5341eb52b27ce766c1086.jpg"},"display_name":"masaomi fujita","fields":["Graphic Design","Art Direction","Branding"]}],"stats":{"views":200,"appreciations":7,"comments":0},"for_sale":0},{"id":9021541,"name":"Yokohama Kaigyo Mania","published_on":1369914202,"created_on":1369914083,"modified_on":1392190252,"url":"http:\/\/www.behance.net\/gallery\/Yokohama-Kaigyo-Mania\/9021541","privacy":"public","fields":["Art Direction","Branding","Graphic Design"],"covers":{"404":"http:\/\/m1.behance.net\/rendition\/projects\/9021541\/404\/aa723e1382cd475cd9d47b70a86f43f4.jpg","202":"http:\/\/m1.behance.net\/rendition\/projects\/9021541\/orig\/aa723e1382cd475cd9d47b70a86f43f4.jpg","230":"http:\/\/m1.behance.net\/rendition\/projects\/9021541\/230\/aa723e1382cd475cd9d47b70a86f43f4.jpg","115":"http:\/\/m1.behance.net\/rendition\/projects\/9021541\/115\/aa723e1382cd475cd9d47b70a86f43f4.jpg"},"mature_content":0,"mature_access":"allowed","owners":[{"id":2743223,"first_name":"masaomi","last_name":"fujita","username":"tegusu","city":"Tokyo","state":"","country":"Japan","company":"tegusu","occupation":"Art Director","created_on":1369104115,"url":"http:\/\/www.behance.net\/tegusu","images":{"50":"http:\/\/m1.behance.net\/profiles24\/2743223\/50x74a6574c07d5341eb52b27ce766c1086.jpg","115":"http:\/\/m1.behance.net\/profiles24\/2743223\/115x74a6574c07d5341eb52b27ce766c1086.jpg","138":"http:\/\/m1.behance.net\/profiles24\/2743223\/74a6574c07d5341eb52b27ce766c1086.jpg"},"display_name":"masaomi fujita","fields":["Graphic Design","Art Direction","Branding"]}],"stats":{"views":359,"appreciations":27,"comments":0},"for_sale":0},{"id":164573,"name":"my latest posters for the dutch national ballet","published_on":1231082967,"created_on":1231082622,"modified_on":1354033448,"url":"http:\/\/www.behance.net\/gallery\/my-latest-posters-for-the-dutch-national-ballet\/164573","privacy":"public","fields":["Photography","Graphic Design","Typography"],"covers":{"202":"http:\/\/m1.behance.net\/rendition\/projects\/164573\/orig\/0517471231082576.jpg","115":"http:\/\/m1.behance.net\/rendition\/projects\/164573\/115\/0517471231082576.jpg"},"mature_content":0,"mature_access":"allowed","owners":[{"id":51747,"first_name":"martin","last_name":"pyper","username":"mestudio","city":"Amsterdam","state":"","country":"Netherlands","company":"me studio","occupation":"graphic designer \/ art director","created_on":1191870057,"url":"http:\/\/www.behance.net\/mestudio","images":{"50":"http:\/\/m1.behance.net\/profiles\/51747\/50x0517471249037308.jpg","115":"http:\/\/m1.behance.net\/profiles\/51747\/115x0517471249037308.jpg","138":"http:\/\/m1.behance.net\/profiles\/51747\/0517471249037308.jpg"},"display_name":"martin pyper","fields":["Graphic Design","Typography","Photography"]}],"stats":{"views":6627,"appreciations":220,"comments":36},"for_sale":0,"features":[{"featured_on":1232424001,"url":"http:\/\/www.behance.net\/gallery\/my-latest-posters-for-the-dutch-national-ballet\/164573","site":{"id":1,"name":"Behance.net","key":"net","icon":"http:\/\/a2.behance.net\/img\/site\/favicon.ico","url":"http:\/\/www.behance.net","domain":"www.behance.net","ribbon":{"image":"http:\/\/a2.behance.net\/img\/galleries\/ribbons\/1x\/net.png","image_2x":"http:\/\/a2.behance.net\/img\/galleries\/ribbons\/2x\/net@2x.png"}}}]},{"id":2014673,"name":"Travel Brochure Front & Back","published_on":1314190587,"created_on":1314189826,"modified_on":1354650794,"url":"http:\/\/www.behance.net\/gallery\/Travel-Brochure-Front-Back\/2014673","privacy":"public","fields":["Graphic Design"],"covers":{"202":"http:\/\/m1.behance.net\/rendition\/projects\/2014673\/orig\/84a2abf84ee6f2bae17b1d6d2be24748.jpg","115":"http:\/\/m1.behance.net\/rendition\/projects\/2014673\/115\/84a2abf84ee6f2bae17b1d6d2be24748.jpg"},"mature_content":0,"mature_access":"allowed","owners":[{"id":602177,"first_name":"Bill","last_name":"Swearingen","username":"bill1","city":"Norfolk","state":"Virginia","country":"United States","company":"","occupation":"","created_on":1314189077,"url":"http:\/\/www.behance.net\/bill1","images":{"50":"http:\/\/a2.behance.net\/img\/profile\/no-image-50.jpg?cb=586349672","115":"http:\/\/a2.behance.net\/img\/profile\/no-image-115.jpg?cb=586349672","138":"http:\/\/a2.behance.net\/img\/profile\/no-image-138.jpg?cb=586349672"},"display_name":"Bill Swearingen","fields":["Graphic Design"]}],"stats":{"views":201,"appreciations":2,"comments":0},"for_sale":0},{"id":2815601,"name":"David Carson Biography","published_on":1327202974,"created_on":1325906766,"modified_on":1376509495,"url":"http:\/\/www.behance.net\/gallery\/David-Carson-Biography\/2815601","privacy":"public","fields":["Graphic Design","Print Design"],"covers":{"202":"http:\/\/m1.behance.net\/rendition\/projects\/2815601\/orig\/a947b0af97c69f2dc6f668a3e4ebc907.png","115":"http:\/\/m1.behance.net\/rendition\/projects\/2815601\/115\/a947b0af97c69f2dc6f668a3e4ebc907.png"},"mature_content":0,"mature_access":"allowed","owners":[{"id":689218,"first_name":"Elizabeth","last_name":"Jacobs","username":"eljacobs","city":"Lenexa","state":"Kansas","country":"United States","company":"Garmin International, Inc.","occupation":"Associate Web Designer","created_on":1318372862,"url":"http:\/\/www.behance.net\/eljacobs","images":{"50":"http:\/\/m1.behance.net\/profiles20\/689218\/50x477135c1ab901958e32f95a81f3f9dd8.png","115":"http:\/\/m1.behance.net\/profiles20\/689218\/115x477135c1ab901958e32f95a81f3f9dd8.png","138":"http:\/\/m1.behance.net\/profiles20\/689218\/477135c1ab901958e32f95a81f3f9dd8.png"},"display_name":"Elizabeth Jacobs","fields":["Graphic Design","Animation","Computer Animation"]}],"stats":{"views":1123,"appreciations":30,"comments":0},"for_sale":0},{"id":3586137,"name":"New Year\u2019s Stories","published_on":1333878612,"created_on":1333875072,"modified_on":1374844134,"url":"http:\/\/www.behance.net\/gallery\/New-Years-Stories\/3586137","privacy":"public","fields":["Graphic Design","Illustration","Packaging"],"covers":{"202":"http:\/\/m1.behance.net\/rendition\/projects\/3586137\/orig\/98417c8447351f090e9460684dad5926.png","115":"http:\/\/m1.behance.net\/rendition\/projects\/3586137\/115\/98417c8447351f090e9460684dad5926.png"},"mature_content":0,"mature_access":"allowed","owners":[{"id":1047893,"first_name":"Olga","last_name":"Mosina","username":"mosinaolga","city":"Yekaterinburg","state":"","country":"Russian Federation","company":"","occupation":"","created_on":1333307561,"url":"http:\/\/www.behance.net\/mosinaolga","images":{"50":"http:\/\/m1.behance.net\/profiles21\/1047893\/50xba8fa49f1f2e87c0934d9cc65a4f6203.jpg","115":"http:\/\/m1.behance.net\/profiles21\/1047893\/115xba8fa49f1f2e87c0934d9cc65a4f6203.jpg","138":"http:\/\/m1.behance.net\/profiles21\/1047893\/ba8fa49f1f2e87c0934d9cc65a4f6203.jpg"},"display_name":"Olga Mosina","fields":["Graphic Design","Print Design","Packaging"]}],"stats":{"views":22523,"appreciations":1390,"comments":70},"for_sale":0},{"id":4098537,"name":"L'am\u00e9rique en col\u00e8re","published_on":1340577897,"created_on":1338509474,"modified_on":1381758474,"url":"http:\/\/www.behance.net\/gallery\/Lamrique-en-colere\/4098537","privacy":"public","fields":["Art Direction","Branding","Graphic Design"],"covers":{"202":"http:\/\/m1.behance.net\/rendition\/projects\/4098537\/orig\/7356d473cb622740328dbae9179fb3f2.jpg","115":"http:\/\/m1.behance.net\/rendition\/projects\/4098537\/115\/7356d473cb622740328dbae9179fb3f2.jpg"},"mature_content":0,"mature_access":"allowed","owners":[{"id":106580,"first_name":"Philippe","last_name":"Cossette","username":"philcossette","city":"London","state":"","country":"United Kingdom","company":"Studio Juice","occupation":"Graphic Designer","created_on":1243606672,"url":"http:\/\/www.behance.net\/philcossette","images":{"50":"http:\/\/m1.behance.net\/profiles2\/106580\/50xd96a4351838045165d0d99a31f8169cb.jpg","115":"http:\/\/m1.behance.net\/profiles2\/106580\/115xd96a4351838045165d0d99a31f8169cb.jpg","138":"http:\/\/m1.behance.net\/profiles2\/106580\/d96a4351838045165d0d99a31f8169cb.jpg"},"display_name":"Philippe Cossette","fields":["Art Direction","Graphic Design","Branding"]}],"stats":{"views":1697,"appreciations":201,"comments":18},"for_sale":0},{"id":4487215,"name":"Logo Design","published_on":1341967770,"created_on":1341966712,"modified_on":1353560054,"url":"http:\/\/www.behance.net\/gallery\/Logo-Design\/4487215","privacy":"public","fields":["Art Direction","Digital Art","Graphic Design"],"covers":{"202":"http:\/\/m1.behance.net\/rendition\/projects\/4487215\/orig\/7c9c0786fa99f6ab4fed5d9377160203.jpg","115":"http:\/\/m1.behance.net\/rendition\/projects\/4487215\/115\/7c9c0786fa99f6ab4fed5d9377160203.jpg"},"mature_content":0,"mature_access":"allowed","owners":[{"id":888387,"first_name":"frederic","last_name":"tiberghien","username":"ftiberghien","city":"Orange","state":"California","country":"United States","company":"","occupation":"Creative Manager","created_on":1327539272,"url":"http:\/\/www.behance.net\/ftiberghien","images":{"50":"http:\/\/m1.behance.net\/profiles15\/888387\/50x6606e5dc9c6a0c15c44f1d78a6c9ba90.png","115":"http:\/\/m1.behance.net\/profiles15\/888387\/115x6606e5dc9c6a0c15c44f1d78a6c9ba90.png","138":"http:\/\/m1.behance.net\/profiles15\/888387\/6606e5dc9c6a0c15c44f1d78a6c9ba90.png"},"display_name":"frederic tiberghien","fields":["Photography","Retouching","Graphic Design"]}],"stats":{"views":171,"appreciations":6,"comments":0},"for_sale":0},{"id":4708737,"name":"Mintrans","published_on":1343989422,"created_on":1343928400,"modified_on":1349788790,"url":"http:\/\/www.behance.net\/gallery\/Mintrans\/4708737","privacy":"public","fields":["Graphic Design"],"covers":{"202":"http:\/\/m1.behance.net\/rendition\/projects\/4708737\/orig\/6479b84ce92e6023ceb6800ad2b3bcd7.jpg","115":"http:\/\/m1.behance.net\/rendition\/projects\/4708737\/115\/6479b84ce92e6023ceb6800ad2b3bcd7.jpg"},"mature_content":0,"mature_access":"allowed","owners":[{"id":98487,"first_name":"N3 Design","last_name":"","username":"n3design","city":"Moscow","state":"","country":"Russian Federation","company":"","occupation":"","created_on":1237979772,"url":"http:\/\/www.behance.net\/n3design","images":{"50":"http:\/\/m1.behance.net\/profiles2\/98487\/50xb5a68e6c995e75590585583f3fcfe4b6.jpg","115":"http:\/\/m1.behance.net\/profiles2\/98487\/115xb5a68e6c995e75590585583f3fcfe4b6.jpg","138":"http:\/\/m1.behance.net\/profiles2\/98487\/b5a68e6c995e75590585583f3fcfe4b6.jpg"},"display_name":"N3 Design","fields":["Motion Graphics","Graphic Design","Advertising"]}],"stats":{"views":2046,"appreciations":78,"comments":2},"for_sale":0}],"http_code":200}