{"projects":[{"id":11180833,"name":"Moon thief","published_on":1380454960,"created_on":1380454741,"modified_on":1380454960,"url":"http:\/\/www.behance.net\/gallery\/Moon-thief\/11180833","privacy":"public","fields":["Character Design","Graphic Design","Illustration"],"covers":{"404":"http:\/\/m1.behance.net\/rendition\/projects\/11180833\/404\/72df2d0368117871e028526b2ca1cd9f.jpeg","202":"http:\/\/m1.behance.net\/rendition\/projects\/11180833\/orig\/72df2d0368117871e028526b2ca1cd9f.jpeg","230":"http:\/\/m1.behance.net\/rendition\/projects\/11180833\/230\/72df2d0368117871e028526b2ca1cd9f.jpeg","115":"http:\/\/m1.behance.net\/rendition\/projects\/11180833\/115\/72df2d0368117871e028526b2ca1cd9f.jpeg"},"mature_content":0,"mature_access":"allowed","owners":[{"id":91409,"first_name":"Nico","last_name":"189","username":"Nico189","city":"Milan","state":"","country":"Italy","location":"Milan, Italy","company":"freelance","occupation":"Graphic designer & illustrator","created_on":1231773904,"url":"http:\/\/www.behance.net\/Nico189","images":{"50":"http:\/\/m1.behance.net\/profiles\/91409\/50x243dab101d278dd6fffa37743694d5a9.jpg","115":"http:\/\/m1.behance.net\/profiles\/91409\/115x243dab101d278dd6fffa37743694d5a9.jpg","138":"http:\/\/m1.behance.net\/profiles\/91409\/243dab101d278dd6fffa37743694d5a9.jpg"},"display_name":"Nico 189","fields":["Graphic Design","Illustration","Typography"]}],"stats":{"views":192,"appreciations":26,"comments":1},"for_sale":0},{"id":11189323,"name":"Hey Ladies! E-commerce de acess\u00f3rios femininos","published_on":1380495806,"created_on":1380495696,"modified_on":1380495806,"url":"http:\/\/www.behance.net\/gallery\/Hey-Ladies-E-commerce-de-acessorios-femininos\/11189323","privacy":"public","fields":["Branding","Fashion","Graphic Design"],"covers":{"404":"http:\/\/m1.behance.net\/rendition\/projects\/11189323\/404\/1714c386dd6754b664b04dfd83b570c9.jpeg","202":"http:\/\/m1.behance.net\/rendition\/projects\/11189323\/orig\/1714c386dd6754b664b04dfd83b570c9.jpeg","230":"http:\/\/m1.behance.net\/rendition\/projects\/11189323\/230\/1714c386dd6754b664b04dfd83b570c9.jpeg","115":"http:\/\/m1.behance.net\/rendition\/projects\/11189323\/115\/1714c386dd6754b664b04dfd83b570c9.jpeg"},"mature_content":0,"mature_access":"allowed","owners":[{"id":715628,"first_name":"Elen","last_name":"Valad\u00e3o","username":"elenvaladao","city":"City","state":"","country":"Brazil","location":"Brazil","company":"","occupation":"Graphic Designer","created_on":1319626408,"url":"http:\/\/www.behance.net\/elenvaladao","images":{"50":"http:\/\/m1.behance.net\/profiles14\/715628\/50xd8842ef99e1d1369e6a4c5b41ada86fc.jpg","115":"http:\/\/m1.behance.net\/profiles14\/715628\/115xd8842ef99e1d1369e6a4c5b41ada86fc.jpg","138":"http:\/\/m1.behance.net\/profiles14\/715628\/d8842ef99e1d1369e6a4c5b41ada86fc.jpg"},"display_name":"Elen Valad\u00e3o","fields":["Graphic Design","Print Design","Branding"]}],"stats":{"views":53,"appreciations":4,"comments":0},"for_sale":0},{"id":1118935,"name":"AS Logo Design","published_on":1300138573,"created_on":1300137954,"modified_on":1354645386,"url":"http:\/\/www.behance.net\/gallery\/AS-Logo-Design\/1118935","privacy":"public","fields":["Design","Graphic Design","Web Design"],"covers":{"202":"http:\/\/m1.behance.net\/rendition\/projects\/1118935\/orig\/4f20f8bd7bfd2fd30c2b5401d5b447e6.jpg","115":"http:\/\/m1.behance.net\/rendition\/projects\/1118935\/115\/4f20f8bd7bfd2fd30c2b5401d5b447e6.jpg"},"mature_content":0,"mature_access":"allowed","owners":[{"id":199814,"first_name":"Andrew","last_name":"Solesbury","username":"andrewsolesbury","city":"Milton Keynes","state":"","country":"United Kingdom","location":"Milton Keynes, United Kingdom","company":"","occupation":"","created_on":1280050665,"url":"http:\/\/www.behance.net\/andrewsolesbury","images":{"50":"http:\/\/m1.behance.net\/profiles4\/199814\/50xb51b57b4fb325e041c254d9e4b0885f8.jpg","115":"http:\/\/m1.behance.net\/profiles4\/199814\/115xb51b57b4fb325e041c254d9e4b0885f8.jpg","138":"http:\/\/m1.behance.net\/profiles4\/199814\/b51b57b4fb325e041c254d9e4b0885f8.jpg"},"display_name":"Andrew Solesbury","fields":["Product Design","Design","Industrial Design"]}],"stats":{"views":336,"appreciations":8,"comments":0},"for_sale":0},{"id":11195417,"name":"Saudi Arabia","published_on":1380533394,"created_on":1380533310,"modified_on":1380533394,"url":"http:\/\/www.behance.net\/gallery\/Saudi-Arabia\/11195417","privacy":"public","fields":["Advertising","Digital Photography","Graphic Design"],"covers":{"404":"http:\/\/m1.behance.net\/rendition\/projects\/11195417\/404\/48df3f2016cc166a879dca9425055e9b.jpeg","202":"http:\/\/m1.behance.net\/rendition\/projects\/11195417\/orig\/48df3f2016cc166a879dca9425055e9b.jpeg","230":"http:\/\/m1.behance.net\/rendition\/projects\/11195417\/230\/48df3f2016cc166a879dca9425055e9b.jpeg","115":"http:\/\/m1.behance.net\/rendition\/projects\/11195417\/115\/48df3f2016cc166a879dca9425055e9b.jpeg"},"mature_content":0,"mature_access":"allowed","owners":[{"id":3111969,"first_name":"Mohammad","last_name":"abu khadra","username":"design86","city":"Riyadh","state":"","country":"Saudi Arabia","location":"Riyadh, Saudi Arabia","company":"Design One","occupation":"Graphic Design","created_on":1374016266,"url":"http:\/\/www.behance.net\/design86","images":{"50":"http:\/\/m1.behance.net\/profiles23\/3111969\/50x25c050d8f63b005aae7d870370a35905.","115":"http:\/\/m1.behance.net\/profiles23\/3111969\/115x25c050d8f63b005aae7d870370a35905.","138":"http:\/\/m1.behance.net\/profiles23\/3111969\/25c050d8f63b005aae7d870370a35905."},"display_name":"Mohammad abu khadra","fields":["Advertising","Graphic Design","Creative Direction"]}],"stats":{"views":82,"appreciations":4,"comments":0},"for_sale":0},{"id":1119597,"name":"Psi","published_on":1300145949,"created_on":1300145738,"modified_on":1353365469,"url":"http:\/\/www.behance.net\/gallery\/Psi\/1119597","privacy":"public","fields":["Graphic Design"],"covers":{"202":"http:\/\/m1.behance.net\/rendition\/projects\/1119597\/orig\/733328db6a3bdc1c67dd98855ac14d2c.jpg","115":"http:\/\/m1.behance.net\/rendition\/projects\/1119597\/115\/733328db6a3bdc1c67dd98855ac14d2c.jpg"},"mature_content":0,"mature_access":"allowed","owners":[{"id":364109,"first_name":"Jarard","last_name":"Anderson","username":"andersondesigns","city":"Muskegon","state":"Michigan","country":"United States","location":"Muskegon, MI, USA","company":"Anderson Designs","occupation":"","created_on":1300137947,"url":"http:\/\/www.behance.net\/andersondesigns","images":{"50":"http:\/\/m1.behance.net\/profiles19\/364109\/50xb16d9c6203e0b4f2d32c32d10cb3e9b1.jpg","115":"http:\/\/m1.behance.net\/profiles19\/364109\/115xb16d9c6203e0b4f2d32c32d10cb3e9b1.jpg","138":"http:\/\/m1.behance.net\/profiles19\/364109\/b16d9c6203e0b4f2d32c32d10cb3e9b1.jpg"},"display_name":"Jarard Anderson","fields":["Graphic Design","Illustration","Design"]}],"stats":{"views":64,"appreciations":0,"comments":0},"for_sale":0},{"id":1119641,"name":"Dance. Or. Die. Posters","published_on":1300147364,"created_on":1300146555,"modified_on":1353365470,"url":"http:\/\/www.behance.net\/gallery\/Dance-Or-Die-Posters\/1119641","privacy":"public","fields":["Advertising","Graphic Design"],"covers":{"202":"http:\/\/m1.behance.net\/rendition\/projects\/1119641\/orig\/51757e352c6499b36a9b20e5b86687a3.jpg","115":"http:\/\/m1.behance.net\/rendition\/projects\/1119641\/115\/51757e352c6499b36a9b20e5b86687a3.jpg"},"mature_content":0,"mature_access":"allowed","owners":[{"id":201617,"first_name":"Rio","last_name":"Macchia","username":"RioMacchia","city":"Santa Rosa","state":"California","country":"United States","location":"Santa Rosa, CA, USA","company":"Freelance","occupation":"","created_on":1280267134,"url":"http:\/\/www.behance.net\/RioMacchia","images":{"50":"http:\/\/a2.behance.net\/img\/profile\/no-image-50.jpg?cb=485136376","115":"http:\/\/a2.behance.net\/img\/profile\/no-image-115.jpg?cb=485136376","138":"http:\/\/a2.behance.net\/img\/profile\/no-image-138.jpg?cb=485136376"},"display_name":"Rio Macchia","fields":["Advertising","Graphic Design","Street Art"]}],"stats":{"views":37,"appreciations":0,"comments":0},"for_sale":1},{"id":11199719,"name":"church flyer","published_on":1380550318,"created_on":1380550246,"modified_on":1380550318,"url":"http:\/\/www.behance.net\/gallery\/church-flyer\/11199719","privacy":"public","fields":["Graphic Design","Icon Design"],"covers":{"404":"http:\/\/m1.behance.net\/rendition\/projects\/11199719\/404\/f8f70d73450430a9f165c3c4ebb5b9d5.png","202":"http:\/\/m1.behance.net\/rendition\/projects\/11199719\/orig\/f8f70d73450430a9f165c3c4ebb5b9d5.png","230":"http:\/\/m1.behance.net\/rendition\/projects\/11199719\/230\/f8f70d73450430a9f165c3c4ebb5b9d5.png","115":"http:\/\/m1.behance.net\/rendition\/projects\/11199719\/115\/f8f70d73450430a9f165c3c4ebb5b9d5.png"},"mature_content":0,"mature_access":"allowed","owners":[{"id":2854065,"first_name":"ade","last_name":"omorgbe","username":"ade_the_director","city":"London","state":"","country":"United Kingdom","location":"London, United Kingdom","company":"","occupation":"Graphic designer, Fine Art, Film making","created_on":1370818853,"url":"http:\/\/www.behance.net\/ade_the_director","images":{"50":"http:\/\/m1.behance.net\/profiles6\/2854065\/50x004293637294658b7b59d894a5667654.jpg","115":"http:\/\/m1.behance.net\/profiles6\/2854065\/115x004293637294658b7b59d894a5667654.jpg","138":"http:\/\/m1.behance.net\/profiles6\/2854065\/004293637294658b7b59d894a5667654.jpg"},"display_name":"ade omorgbe","fields":["Graphic Design","Typography","Illustration"]}],"stats":{"views":14,"appreciations":0,"comments":0},"for_sale":0},{"id":11203163,"name":"I Transform - Art work relay","published_on":1380570242,"created_on":1380559949,"modified_on":1387610701,"url":"http:\/\/www.behance.net\/gallery\/I-Transform-Art-work-relay\/11203163","privacy":"public","fields":["Art Direction","Digital Art","Graphic Design"],"covers":{"404":"http:\/\/m1.behance.net\/rendition\/projects\/11203163\/404\/3a1733489f866fba492d7e79ea98e754.jpeg","202":"http:\/\/m1.behance.net\/rendition\/projects\/11203163\/orig\/3a1733489f866fba492d7e79ea98e754.jpeg","230":"http:\/\/m1.behance.net\/rendition\/projects\/11203163\/230\/3a1733489f866fba492d7e79ea98e754.jpeg","115":"http:\/\/m1.behance.net\/rendition\/projects\/11203163\/115\/3a1733489f866fba492d7e79ea98e754.jpeg"},"mature_content":0,"mature_access":"allowed","owners":[{"id":164495,"first_name":"Chul hwee","last_name":"Kim","username":"visual-boom","city":"Seoul","state":"","country":"Korea, Republic of","location":"Seoul, Korea, Republic of","company":"YG ENTERTAINMENT","occupation":"Art Director","created_on":1271599429,"url":"http:\/\/www.behance.net\/visual-boom","images":{"50":"http:\/\/m1.behance.net\/profiles5\/164495\/50x01644951272557134.jpg","115":"http:\/\/m1.behance.net\/profiles5\/164495\/115x01644951272557134.jpg","138":"http:\/\/m1.behance.net\/profiles5\/164495\/01644951272557134.jpg"},"display_name":"Chul hwee Kim","fields":["Graphic Design","Print Design","Art Direction"]}],"stats":{"views":1195,"appreciations":120,"comments":11},"for_sale":0},{"id":1120677,"name":"Opinion Space","published_on":1300181005,"created_on":1300173921,"modified_on":1353365537,"url":"http:\/\/www.behance.net\/gallery\/Opinion-Space\/1120677","privacy":"public","fields":["UI\/UX","Graphic Design"],"covers":{"202":"http:\/\/m1.behance.net\/rendition\/projects\/1120677\/orig\/c2345a82e065430b7ee6e93a1c8ad158.png","115":"http:\/\/m1.behance.net\/rendition\/projects\/1120677\/115\/c2345a82e065430b7ee6e93a1c8ad158.png"},"mature_content":0,"mature_access":"allowed","owners":[{"id":335633,"first_name":"Alex","last_name":"Mandel","username":"alexmandel","city":"Berkeley","state":"California","country":"United States","location":"Berkeley, CA, USA","company":"UC Berkeley","occupation":"Student","created_on":1298497396,"url":"http:\/\/www.behance.net\/alexmandel","images":{"50":"http:\/\/m1.behance.net\/profiles26\/335633\/50x23a108a92ec7edf3fba39f7855b69f91.png","115":"http:\/\/m1.behance.net\/profiles26\/335633\/115x23a108a92ec7edf3fba39f7855b69f91.png","138":"http:\/\/m1.behance.net\/profiles26\/335633\/23a108a92ec7edf3fba39f7855b69f91.png"},"display_name":"Alex Mandel","fields":["UI\/UX","Interaction Design","Graphic Design"]}],"stats":{"views":151,"appreciations":1,"comments":0},"for_sale":0},{"id":112110,"name":"Magazine '60 parallel'","published_on":1218318147,"created_on":1217322293,"modified_on":1373564195,"url":"http:\/\/www.behance.net\/gallery\/Magazine-60-parallel\/112110","privacy":"public","fields":["Publishing","Graphic Design"],"covers":{"404":"http:\/\/m1.behance.net\/rendition\/projects\/112110\/404\/98fe333f49d7108d3c9d3692c4bafd53.jpg","202":"http:\/\/m1.behance.net\/rendition\/projects\/112110\/orig\/98fe333f49d7108d3c9d3692c4bafd53.jpg","230":"http:\/\/m1.behance.net\/rendition\/projects\/112110\/230\/98fe333f49d7108d3c9d3692c4bafd53.jpg","115":"http:\/\/m1.behance.net\/rendition\/projects\/112110\/115\/98fe333f49d7108d3c9d3692c4bafd53.jpg"},"mature_content":0,"mature_access":"allowed","owners":[{"id":77750,"first_name":"Slava","last_name":"Strizh","username":"slavastrizh","city":"Saint Petersburg","state":"","country":"Russian Federation","location":"Saint Petersburg, Russian Federation","company":"","occupation":"Designer & Art Director","created_on":1216833980,"url":"http:\/\/www.behance.net\/slavastrizh","images":{"50":"http:\/\/m1.behance.net\/profiles\/77750\/50xce06bc8f24cd3fe6cfbc949f750f5ab3.png","115":"http:\/\/m1.behance.net\/profiles\/77750\/115xce06bc8f24cd3fe6cfbc949f750f5ab3.png","138":"http:\/\/m1.behance.net\/profiles\/77750\/ce06bc8f24cd3fe6cfbc949f750f5ab3.png"},"display_name":"Slava Strizh","fields":["Graphic Design","Art Direction","Web Design"]},{"id":92234,"first_name":"Nashihaura","last_name":"","username":"viracheff","city":"Surgut","state":"","country":"Russian Federation","location":"Surgut, Russian Federation","company":"Nashihaura","occupation":"","created_on":1232466312,"url":"http:\/\/www.behance.net\/viracheff","images":{"50":"http:\/\/m1.behance.net\/profiles4\/92234\/50x0922341232886301.png","115":"http:\/\/m1.behance.net\/profiles4\/92234\/115x0922341232886301.png","138":"http:\/\/m1.behance.net\/profiles4\/92234\/0922341232886301.png"},"display_name":"Nashihaura","fields":["Publishing","Graphic Design"]}],"stats":{"views":2300,"appreciations":57,"comments":2},"for_sale":0},{"id":11220813,"name":"MSS Logo Design","published_on":1380633931,"created_on":1380633796,"modified_on":1380633931,"url":"http:\/\/www.behance.net\/gallery\/MSS-Logo-Design\/11220813","privacy":"public","fields":["Graphic Design"],"covers":{"404":"http:\/\/m1.behance.net\/rendition\/projects\/11220813\/404\/5190060d8c862a43bc5fde1324aa6271.jpeg","202":"http:\/\/m1.behance.net\/rendition\/projects\/11220813\/orig\/5190060d8c862a43bc5fde1324aa6271.jpeg","230":"http:\/\/m1.behance.net\/rendition\/projects\/11220813\/230\/5190060d8c862a43bc5fde1324aa6271.jpeg","115":"http:\/\/m1.behance.net\/rendition\/projects\/11220813\/115\/5190060d8c862a43bc5fde1324aa6271.jpeg"},"mature_content":0,"mature_access":"allowed","owners":[{"id":2632415,"first_name":"Shun","last_name":"Matsumoto","username":"abstract_concept","city":"Tokyo","state":"","country":"Japan","location":"Tokyo, Japan","company":"Abstract Concept","occupation":"Graphic Designer, Digital Artist","created_on":1367465010,"url":"http:\/\/www.behance.net\/abstract_concept","images":{"50":"http:\/\/m1.behance.net\/profiles12\/2632415\/50x638e497c38b1c3117994e3b49b90fd88.jpg","115":"http:\/\/m1.behance.net\/profiles12\/2632415\/115x638e497c38b1c3117994e3b49b90fd88.jpg","138":"http:\/\/m1.behance.net\/profiles12\/2632415\/638e497c38b1c3117994e3b49b90fd88.jpg"},"display_name":"Shun Matsumoto","fields":["Digital Art","Graphic Design","Product Design"]}],"stats":{"views":36,"appreciations":1,"comments":0},"for_sale":0},{"id":11221203,"name":"Fractured Fairytales","published_on":1380635432,"created_on":1380634940,"modified_on":1383304979,"url":"http:\/\/www.behance.net\/gallery\/Fractured-Fairytales\/11221203","privacy":"public","fields":["Graphic Design","Illustration","Print Design"],"covers":{"404":"http:\/\/m1.behance.net\/rendition\/projects\/11221203\/404\/a4c4301b95424f539ea88d4b2933eec8.png","202":"http:\/\/m1.behance.net\/rendition\/projects\/11221203\/orig\/a4c4301b95424f539ea88d4b2933eec8.png","230":"http:\/\/m1.behance.net\/rendition\/projects\/11221203\/230\/a4c4301b95424f539ea88d4b2933eec8.png","115":"http:\/\/m1.behance.net\/rendition\/projects\/11221203\/115\/a4c4301b95424f539ea88d4b2933eec8.png"},"mature_content":0,"mature_access":"allowed","owners":[{"id":3083795,"first_name":"Annika","last_name":"Smit","username":"annikasmit","city":"Newcastle","state":"","country":"Australia","location":"Newcastle, Australia","company":"","occupation":"Student","created_on":1373621635,"url":"http:\/\/www.behance.net\/annikasmit","images":{"50":"http:\/\/m1.behance.net\/profiles13\/3083795\/50x3552041e0586ada9bcedee05ad6f2e48.jpg","115":"http:\/\/m1.behance.net\/profiles13\/3083795\/115x3552041e0586ada9bcedee05ad6f2e48.jpg","138":"http:\/\/m1.behance.net\/profiles13\/3083795\/3552041e0586ada9bcedee05ad6f2e48.jpg"},"display_name":"Annika Smit","fields":["Illustration","Advertising","Print Design"]}],"stats":{"views":59,"appreciations":5,"comments":3},"for_sale":0}],"http_code":200}