{"projects":[{"id":2737363,"name":"Almond Smash Soda: Rebrand","published_on":1324667250,"created_on":1324650163,"modified_on":1354654136,"url":"http:\/\/www.behance.net\/gallery\/Almond-Smash-Soda-Rebrand\/2737363","privacy":"public","fields":["Branding","Graphic Design","Packaging"],"covers":{"202":"http:\/\/m1.behance.net\/rendition\/projects\/2737363\/orig\/bec2577e1765104f4f8152a8bd83bcaa.jpg","115":"http:\/\/m1.behance.net\/rendition\/projects\/2737363\/115\/bec2577e1765104f4f8152a8bd83bcaa.jpg"},"mature_content":0,"mature_access":"allowed","owners":[{"id":607589,"first_name":"Nathaniel","last_name":"Phillips","username":"nphillips","city":"Beacon","state":"New York","country":"United States","location":"Beacon, NY, USA","company":"","occupation":"","created_on":1314493906,"url":"http:\/\/www.behance.net\/nphillips","images":{"50":"http:\/\/m1.behance.net\/profiles23\/607589\/50x0497462a01adeb1727fbd455e6bfdea9.jpg","115":"http:\/\/m1.behance.net\/profiles23\/607589\/115x0497462a01adeb1727fbd455e6bfdea9.jpg","138":"http:\/\/m1.behance.net\/profiles23\/607589\/0497462a01adeb1727fbd455e6bfdea9.jpg"},"display_name":"Nathaniel Phillips","fields":["Graphic Design","Typography","Branding"]}],"stats":{"views":1783,"appreciations":15,"comments":0},"for_sale":0},{"id":2752779,"name":"LAHAB BBQ Restaurant","published_on":1325020742,"created_on":1325020291,"modified_on":1353461145,"url":"http:\/\/www.behance.net\/gallery\/LAHAB-BBQ-Restaurant\/2752779","privacy":"public","fields":["Branding","Calligraphy","Graphic Design"],"covers":{"202":"http:\/\/m1.behance.net\/rendition\/projects\/2752779\/orig\/66af10b16879224f67886b720d0c80d3.jpg","115":"http:\/\/m1.behance.net\/rendition\/projects\/2752779\/115\/66af10b16879224f67886b720d0c80d3.jpg"},"mature_content":0,"mature_access":"allowed","owners":[{"id":682914,"first_name":"Maher","last_name":"A. Housn","username":"Maherahousn","city":"Dubai","state":"","country":"United Arab Emirates","location":"Dubai, United Arab Emirates","company":"mozaiic","occupation":"Art Director","created_on":1318072650,"url":"http:\/\/www.behance.net\/Maherahousn","images":{"50":"http:\/\/m1.behance.net\/profiles8\/682914\/50x541937baac8a9ea3dec895c7bf2f3853.jpg","115":"http:\/\/m1.behance.net\/profiles8\/682914\/115x541937baac8a9ea3dec895c7bf2f3853.jpg","138":"http:\/\/m1.behance.net\/profiles8\/682914\/541937baac8a9ea3dec895c7bf2f3853.jpg"},"display_name":"Maher A. Housn","fields":["Art Direction","Calligraphy","Design"]}],"stats":{"views":4974,"appreciations":321,"comments":19},"for_sale":0},{"id":2762227,"name":"Logopack","published_on":1325174113,"created_on":1325170554,"modified_on":1353461632,"url":"http:\/\/www.behance.net\/gallery\/Logopack\/2762227","privacy":"public","fields":["Branding","Graphic Design","Typography"],"covers":{"202":"http:\/\/m1.behance.net\/rendition\/projects\/2762227\/orig\/9cb6265592d049f036e0b1e1105316e7.jpg","115":"http:\/\/m1.behance.net\/rendition\/projects\/2762227\/115\/9cb6265592d049f036e0b1e1105316e7.jpg"},"mature_content":0,"mature_access":"allowed","owners":[{"id":544860,"first_name":"Adam","last_name":"Nowi\u0144ski","username":"pushdeluxe","city":"Bialystok","state":"","country":"Poland","location":"Bialystok, Poland","company":"","occupation":"Graphic Designer","created_on":1310829215,"url":"http:\/\/www.behance.net\/pushdeluxe","images":{"50":"http:\/\/m1.behance.net\/profiles22\/544860\/50xa3d42b1b39e6266315b31b8125856df4.jpg","115":"http:\/\/m1.behance.net\/profiles22\/544860\/115xa3d42b1b39e6266315b31b8125856df4.jpg","138":"http:\/\/m1.behance.net\/profiles22\/544860\/a3d42b1b39e6266315b31b8125856df4.jpg"},"display_name":"Adam Nowi\u0144ski","fields":["Graphic Design","Branding","Typography"]}],"stats":{"views":6912,"appreciations":479,"comments":59},"for_sale":0},{"id":2776431,"name":"1000 emergency corner for \"LUKOIL\"","published_on":1325467181,"created_on":1325466483,"modified_on":1354188474,"url":"http:\/\/www.behance.net\/gallery\/1000-emergency-corner-for-LUKOIL\/2776431","privacy":"public","fields":["Design","Graphic Design","Print Design"],"covers":{"202":"http:\/\/m1.behance.net\/rendition\/projects\/2776431\/orig\/259f1eb37ff20cb830c6aa58e6f8ee0a.jpg","115":"http:\/\/m1.behance.net\/rendition\/projects\/2776431\/115\/259f1eb37ff20cb830c6aa58e6f8ee0a.jpg"},"mature_content":0,"mature_access":"allowed","owners":[{"id":296096,"first_name":"Viacheslav","last_name":"Abramov","username":"vomarbA","city":"Kiev","state":"","country":"Ukraine","location":"Kiev, Ukraine","company":"vomarbA","occupation":"Art Director, Designer, Photographer","created_on":1295243523,"url":"http:\/\/www.behance.net\/vomarbA","images":{"50":"http:\/\/m1.behance.net\/profiles26\/296096\/50xa339567b8637625dc251145a76302727.","115":"http:\/\/m1.behance.net\/profiles26\/296096\/115xa339567b8637625dc251145a76302727.","138":"http:\/\/m1.behance.net\/profiles26\/296096\/a339567b8637625dc251145a76302727."},"display_name":"Viacheslav Abramov","fields":["Graphic Design","Art Direction","Photography"]}],"stats":{"views":696,"appreciations":413,"comments":0},"for_sale":0},{"id":2789059,"name":"Venda Mineira","published_on":1325624641,"created_on":1325623844,"modified_on":1353463090,"url":"http:\/\/www.behance.net\/gallery\/Venda-Mineira\/2789059","privacy":"public","fields":["Graphic Design","Packaging"],"covers":{"202":"http:\/\/m1.behance.net\/rendition\/projects\/2789059\/orig\/77c59f81c1dc3aa87abb82347c630647.png","115":"http:\/\/m1.behance.net\/rendition\/projects\/2789059\/115\/77c59f81c1dc3aa87abb82347c630647.png"},"mature_content":0,"mature_access":"allowed","owners":[{"id":86624,"first_name":"Daniel","last_name":"Sans\u00e3o","username":"danielsansao","city":"Rio de Janeiro","state":"","country":"Brazil","location":"Rio de Janeiro, Brazil","company":"Cont\u00e1gio Cria\u00e7\u00e3o","occupation":"Founder, Art Director","created_on":1226596327,"url":"http:\/\/www.behance.net\/danielsansao","images":{"50":"http:\/\/m1.behance.net\/profiles\/86624\/50x0866241226635798.jpg","115":"http:\/\/m1.behance.net\/profiles\/86624\/115x0866241226635798.jpg","138":"http:\/\/m1.behance.net\/profiles\/86624\/0866241226635798.jpg"},"display_name":"Daniel Sans\u00e3o","fields":["Graphic Design","Web Design","Packaging"]}],"stats":{"views":1147,"appreciations":34,"comments":2},"for_sale":0},{"id":2793615,"name":"Nokaut.pl Headquarters","published_on":1325683420,"created_on":1325680872,"modified_on":1353463330,"url":"http:\/\/www.behance.net\/gallery\/Nokautpl-Headquarters\/2793615","privacy":"public","fields":["Digital Art","Graphic Design","Street Art"],"covers":{"202":"http:\/\/m1.behance.net\/rendition\/projects\/2793615\/orig\/ff0d5a154c9bc20c7d8b9f355717c1c8.jpg","115":"http:\/\/m1.behance.net\/rendition\/projects\/2793615\/115\/ff0d5a154c9bc20c7d8b9f355717c1c8.jpg"},"mature_content":0,"mature_access":"allowed","owners":[{"id":477531,"first_name":"Marek","last_name":"Rybowski","username":"marek_rybowski","city":"City","state":"","country":"Poland","location":"Poland","company":"looney.pl","occupation":"","created_on":1306852368,"url":"http:\/\/www.behance.net\/marek_rybowski","images":{"50":"http:\/\/m1.behance.net\/profiles19\/477531\/50xdb6413c62d298723b9dc763550c7da10.jpg","115":"http:\/\/m1.behance.net\/profiles19\/477531\/115xdb6413c62d298723b9dc763550c7da10.jpg","138":"http:\/\/m1.behance.net\/profiles19\/477531\/db6413c62d298723b9dc763550c7da10.jpg"},"display_name":"Marek Rybowski","fields":["Street Art","Painting","Graffiti"]}],"stats":{"views":500,"appreciations":34,"comments":1},"for_sale":0},{"id":2803723,"name":"My Brother Rifle. (Revisited)","published_on":1325783984,"created_on":1325783001,"modified_on":1366277788,"url":"http:\/\/www.behance.net\/gallery\/My-Brother-Rifle-(Revisited)\/2803723","privacy":"public","fields":["Graphic Design","Illustration","Typography"],"covers":{"404":"http:\/\/m1.behance.net\/rendition\/projects\/2803723\/404\/035f90cbb4931a8a334b8d9b4aa585bc.jpg","202":"http:\/\/m1.behance.net\/rendition\/projects\/2803723\/orig\/035f90cbb4931a8a334b8d9b4aa585bc.jpg","230":"http:\/\/m1.behance.net\/rendition\/projects\/2803723\/230\/035f90cbb4931a8a334b8d9b4aa585bc.jpg","115":"http:\/\/m1.behance.net\/rendition\/projects\/2803723\/115\/035f90cbb4931a8a334b8d9b4aa585bc.jpg"},"mature_content":0,"mature_access":"allowed","owners":[{"id":838899,"first_name":"Davide","last_name":"Barco","username":"davidebarco","city":"Milano","state":"","country":"Italy","location":"Milano, Italy","company":"Freelance","occupation":"Art Director, Illustrator, Candy Addicted","created_on":1325770432,"url":"http:\/\/www.behance.net\/davidebarco","images":{"50":"http:\/\/m1.behance.net\/profiles7\/838899\/50x5a7a33c732a0a21c30086d3c667e1b25.jpg","115":"http:\/\/m1.behance.net\/profiles7\/838899\/115x5a7a33c732a0a21c30086d3c667e1b25.jpg","138":"http:\/\/m1.behance.net\/profiles7\/838899\/5a7a33c732a0a21c30086d3c667e1b25.jpg"},"display_name":"Davide Barco","fields":["Illustration","Character Design","Graphic Design"]}],"stats":{"views":468,"appreciations":39,"comments":6},"for_sale":0},{"id":2818203,"name":"MUSIC LIFE","published_on":1325957481,"created_on":1325956059,"modified_on":1353464674,"url":"http:\/\/www.behance.net\/gallery\/MUSIC-LIFE\/2818203","privacy":"public","fields":["Music","Graphic Design","Fashion Styling"],"covers":{"202":"http:\/\/m1.behance.net\/rendition\/projects\/2818203\/orig\/768d5818b45fd79e24bcff1c5cefd42e.jpg","115":"http:\/\/m1.behance.net\/rendition\/projects\/2818203\/115\/768d5818b45fd79e24bcff1c5cefd42e.jpg"},"mature_content":0,"mature_access":"allowed","owners":[{"id":127542,"first_name":"Sorghin","last_name":"","username":"Sorghin","city":"Managua","state":"","country":"Nicaragua","location":"Managua, Nicaragua","company":"Ogilvy Nicaragua","occupation":"","created_on":1255133571,"url":"http:\/\/www.behance.net\/Sorghin","images":{"50":"http:\/\/m1.behance.net\/profiles2\/127542\/50xf50a8c8705d8fa74fc91b51a63ebec58.jpg","115":"http:\/\/m1.behance.net\/profiles2\/127542\/115xf50a8c8705d8fa74fc91b51a63ebec58.jpg","138":"http:\/\/m1.behance.net\/profiles2\/127542\/f50a8c8705d8fa74fc91b51a63ebec58.jpg"},"display_name":"Sorghin","fields":["Music","Fashion Styling","Painting"]}],"stats":{"views":257,"appreciations":17,"comments":10},"for_sale":1},{"id":2832393,"name":"URBAN BURGER RESTAURANT","published_on":1326134730,"created_on":1326132072,"modified_on":1353465467,"url":"http:\/\/www.behance.net\/gallery\/URBAN-BURGER-RESTAURANT\/2832393","privacy":"public","fields":["Graphic Design","Illustration"],"covers":{"202":"http:\/\/m1.behance.net\/rendition\/projects\/2832393\/orig\/1a029e4fb2d8ae6bbf7c8c1d871bdb11.jpg","115":"http:\/\/m1.behance.net\/rendition\/projects\/2832393\/115\/1a029e4fb2d8ae6bbf7c8c1d871bdb11.jpg"},"mature_content":0,"mature_access":"allowed","owners":[{"id":677242,"first_name":"Marcassola","last_name":"","username":"marcassola","city":"Barcelona","state":"","country":"Spain","location":"Barcelona, Spain","company":"Marcassola","occupation":"Illustrator, graphic designer","created_on":1317809564,"url":"http:\/\/www.behance.net\/marcassola","images":{"50":"http:\/\/m1.behance.net\/profiles11\/677242\/50x8931da2725b7abd63a0c3b0464b89ae2.jpg","115":"http:\/\/m1.behance.net\/profiles11\/677242\/115x8931da2725b7abd63a0c3b0464b89ae2.jpg","138":"http:\/\/m1.behance.net\/profiles11\/677242\/8931da2725b7abd63a0c3b0464b89ae2.jpg"},"display_name":"Marcassola","fields":["Illustration","Character Design","Branding"]}],"stats":{"views":424,"appreciations":26,"comments":7},"for_sale":1},{"id":2833233,"name":"Prints","published_on":1326146406,"created_on":1326138112,"modified_on":1354654543,"url":"http:\/\/www.behance.net\/gallery\/Prints\/2833233","privacy":"public","fields":["Graphic Design","Print Design","Street Art"],"covers":{"202":"http:\/\/m1.behance.net\/rendition\/projects\/2833233\/orig\/ae4a47afce4e57e53bdf0e1f2bae2b5c.jpg","115":"http:\/\/m1.behance.net\/rendition\/projects\/2833233\/115\/ae4a47afce4e57e53bdf0e1f2bae2b5c.jpg"},"mature_content":0,"mature_access":"allowed","owners":[{"id":847749,"first_name":"Fiji","last_name":"","username":"Fiji","city":"Liverpool","state":"","country":"United Kingdom","location":"Liverpool, United Kingdom","company":"","occupation":"","created_on":1326123751,"url":"http:\/\/www.behance.net\/Fiji","images":{"50":"http:\/\/m1.behance.net\/profiles24\/847749\/50xd0501bb5f86a4e7dae57834c7caaf658.png","115":"http:\/\/m1.behance.net\/profiles24\/847749\/115xd0501bb5f86a4e7dae57834c7caaf658.png","138":"http:\/\/m1.behance.net\/profiles24\/847749\/d0501bb5f86a4e7dae57834c7caaf658.png"},"display_name":"Fiji","fields":["Street Art","Print Design","Drawing"]}],"stats":{"views":100,"appreciations":15,"comments":1},"for_sale":0},{"id":2923903,"name":"Unica fine art expo","published_on":1326971962,"created_on":1326971179,"modified_on":1353470870,"url":"http:\/\/www.behance.net\/gallery\/Unica-fine-art-expo\/2923903","privacy":"public","fields":["Art Direction","Graphic Design","Web Design"],"covers":{"202":"http:\/\/m1.behance.net\/rendition\/projects\/2923903\/orig\/87736a06ad26684e35f1a4c019728a03.jpg","115":"http:\/\/m1.behance.net\/rendition\/projects\/2923903\/115\/87736a06ad26684e35f1a4c019728a03.jpg"},"mature_content":0,"mature_access":"allowed","owners":[{"id":438337,"first_name":"Emanuela","last_name":"Ghizzoni","username":"emanuelaghizzoni","city":"Reggio nell Emilia","state":"","country":"Italy","location":"Reggio nell Emilia, Italy","company":"Studio Egg","occupation":"Art","created_on":1304588746,"url":"http:\/\/www.behance.net\/emanuelaghizzoni","images":{"50":"http:\/\/m1.behance.net\/profiles9\/438337\/50x3743e2abbe6d04f4c01d9070814a0663.jpg","115":"http:\/\/m1.behance.net\/profiles9\/438337\/115x3743e2abbe6d04f4c01d9070814a0663.jpg","138":"http:\/\/m1.behance.net\/profiles9\/438337\/3743e2abbe6d04f4c01d9070814a0663.jpg"},"display_name":"Emanuela Ghizzoni","fields":["Graphic Design","Art Direction","Copywriting"]}],"stats":{"views":471,"appreciations":10,"comments":0},"for_sale":0},{"id":2957431,"name":"The Movable Book of Letterforms","published_on":1327331384,"created_on":1327330950,"modified_on":1364832502,"url":"http:\/\/www.behance.net\/gallery\/The-Movable-Book-of-Letterforms\/2957431","privacy":"public","fields":["Graphic Design","Pop-Up","paper engineering"],"covers":{"202":"http:\/\/m1.behance.net\/rendition\/projects\/2957431\/orig\/e512ebed8f9fec3a938911982de8ee37.jpg","115":"http:\/\/m1.behance.net\/rendition\/projects\/2957431\/115\/e512ebed8f9fec3a938911982de8ee37.jpg"},"mature_content":0,"mature_access":"allowed","owners":[{"id":881187,"first_name":"Kevin","last_name":"Steele","username":"MrKevinSteele","city":"Bloomington","state":"Indiana","country":"United States","location":"Bloomington, IN, USA","company":"","occupation":"Graphic Designer","created_on":1327330815,"url":"http:\/\/www.behance.net\/MrKevinSteele","images":{"50":"http:\/\/m1.behance.net\/profiles25\/881187\/50x07d10ebda6be754c040518ce9ca4d71b.jpg","115":"http:\/\/m1.behance.net\/profiles25\/881187\/115x07d10ebda6be754c040518ce9ca4d71b.jpg","138":"http:\/\/m1.behance.net\/profiles25\/881187\/07d10ebda6be754c040518ce9ca4d71b.jpg"},"display_name":"Kevin Steele","fields":["Graphic Design"]}],"stats":{"views":7884,"appreciations":440,"comments":35},"for_sale":0,"features":[{"featured_on":1333569603,"url":"http:\/\/portfolios.aiga.org\/gallery\/The-Movable-Book-of-Letterforms\/2957431","site":{"id":34,"name":"AIGA Member Gallery","key":"aiga","icon":"http:\/\/a2.behance.net\/img\/galleries\/composed\/aiga.png","domain":"portfolios.aiga.org","url":"http:\/\/portfolios.aiga.org","network_id":5,"ribbon":{"image":"http:\/\/a2.behance.net\/img\/galleries\/ribbons\/1x\/aiga.png","image_2x":"http:\/\/a2.behance.net\/img\/galleries\/ribbons\/2x\/aiga@2x.png"}}},{"featured_on":1368714602,"url":"http:\/\/editorialdesignserved.co\/gallery\/The-Movable-Book-of-Letterforms\/2957431","site":{"id":31,"name":"Editorial Design Served","key":"editorial","icon":"http:\/\/a2.behance.net\/img\/galleries\/composed\/editorial.png","domain":"editorialdesignserved.co","url":"http:\/\/editorialdesignserved.co","ribbon":{"image":"http:\/\/a2.behance.net\/img\/galleries\/ribbons\/1x\/editorial.png","image_2x":"http:\/\/a2.behance.net\/img\/galleries\/ribbons\/2x\/editorial@2x.png"}}}]}],"http_code":200}